<?xml version="1.0" encoding="UTF-8"?>
<HostileNPC>
  <id>dargon</id>
  <name>Dargon Woraw</name>
  <description>Coming from the very slavic land of Massachusetts, he&apos;s here to kick ass and chew gum... and he&apos;s all out of ass.</description>
  <iconName>dargon.png</iconName>
  <raceId>1</raceId>
  <classId>1</classId>
  <unique>true</unique>
  <level>1</level>
  <minimumGold>1</minimumGold>
  <maximumGold>5</maximumGold>
  <loottable>
    <entry>
      <string>broken-sword</string>
      <double>50.0</double>
    </entry>
    <entry>
      <string>smallHealthPot</string>
      <double>50.0</double>
    </entry>
  </loottable>
</HostileNPC>